run_tracker/__init__.py
run_tracker/cli.py
run_tracker/run_tracker.py
run_tracker-0.2.3.dist-info/METADATA
run_tracker-0.2.3.dist-info/RECORD
run_tracker-0.2.3.dist-info/WHEEL
run_tracker-0.2.3.dist-info/entry_points.txt
run_tracker-0.2.3.dist-info/top_level.txt
