Metadata-Version: 2.1
Name: run-tracker
Version: 0.2.3
Summary: Simple python package for tracking total distance ran
Home-page: https://github.com/tomstevens9/run_tracker
Author: Tom Stevens
Author-email: tom@thomasjstevens.com
License: MIT license
Keywords: run_tracker
Platform: UNKNOWN
Classifier: Development Status :: 2 - Pre-Alpha
Classifier: Intended Audience :: Developers
Classifier: License :: OSI Approved :: MIT License
Classifier: Natural Language :: English
Classifier: Programming Language :: Python :: 2
Classifier: Programming Language :: Python :: 2.7
Classifier: Programming Language :: Python :: 3
Classifier: Programming Language :: Python :: 3.4
Classifier: Programming Language :: Python :: 3.5
Classifier: Programming Language :: Python :: 3.6
Requires-Dist: Click (>=6.0)
